{
  "slow_build": {
    "Check PR": {
      "data": {
        "2021-04-13T05:47:07Z": 283133.3333333333,
        "2021-04-26T12:31:12Z": 281625.0,
        "2021-05-04T12:44:32Z": 285166.6666666667,
        "2021-05-11T15:13:25Z": 370111.1111111111,
        "2021-05-19T05:26:05Z": 282200.0,
        "2021-06-02T10:08:44Z": 304000.0,
        "2021-06-09T13:21:13Z": 267000.0,
        "2021-06-18T10:23:29Z": 266857.14285714284,
        "2021-06-28T13:02:50Z": 291500.0,
        "2021-07-06T10:30:24Z": 272000.0
      },
      "tool": "Github Actions",
      "total avg": 290359.3253968254,
      "quartiles": {
        "q1": 274406.25,
        "q3": 289916.6666666667,
        "iqr": 15510.416666666686
      },
      "classification": {
        "high_severity": {
          "55": 318000,
          "63": 315000,
          "67": 317000,
          "74": 349000,
          "84": 327000,
          "90": 1181000,
          "96": 320000,
          "105": 439000,
          "107": 316000
        },
        "medium_severity": {
          "44": 293000,
          "45": 291000,
          "49": 304000,
          "51": 291000,
          "58": 307000,
          "60": 298000,
          "61": 297000,
          "62": 302000,
          "68": 303000,
          "69": 307000,
          "71": 308000,
          "80": 301000,
          "81": 293000,
          "85": 298000,
          "87": 310000,
          "89": 305000,
          "97": 298000,
          "100": 300000,
          "101": 313000,
          "106": 308000,
          "111": 293000,
          "115": 296000,
          "117": 291000,
          "121": 307000
        }
      }
    },
    "Build and deploy": {
      "data": {
        "2021-06-18T11:11:31Z": 113000.0
      },
      "tool": "Github Actions",
      "total avg": 113000.0,
      "quartiles": {
        "q1": 113000.0,
        "q3": 113000.0,
        "iqr": 0.0
      },
      "classification": {
        "high_severity": {},
        "medium_severity": {}
      }
    }
  },
  "late_merging": {
    "missed activity": {
      "Fix-styles": 0,
      "add_backgroundLayer": 0,
      "api_bookmarks": 0,
      "change-ui-dropdown-on-flexberry-dropdown": 0,
      "check-all-visibility": 0,
      "dependabot/npm_and_yarn/cached-path-relative-1.1.0": 0,
      "dependabot/npm_and_yarn/dexie-3.2.2": 0,
      "dependabot/npm_and_yarn/follow-redirects-1.14.8": 0,
      "dependabot/npm_and_yarn/handlebars-4.7.7": 0,
      "dependabot/npm_and_yarn/moment-2.29.4": 0,
      "dependabot/npm_and_yarn/moment-timezone-0.5.35": 0,
      "dependabot/npm_and_yarn/mout-1.2.3": 0,
      "dependabot/npm_and_yarn/shell-quote-1.7.3": 0,
      "develop": 0,
      "dropdown-on-gis-search-form": 0,
      "edit-form-at-attrs-panel": 0,
      "feature_228064_identificationAndSearch": 0,
      "feature_228586_Identification_By_Area": 0,
      "feature-161988-add-user-labels": 0,
      "feature-228065-blind-instrument-edit": 0,
      "feature-add-to-aishowFeatureEditForm": 0,
      "feature-ember-update": 0,
      "feature-ember-update-tests": 0,
      "feature-tile-export": 0,
      "fix_edit_maplayer": 0,
      "fix_layerFilter": 0,
      "fix_layerZoomSettings": 0,
      "fix_reloadLayerWithFilter": 0,
      "fix_226713_intersectionForm": 0,
      "fix_227603_mapSearch": 0,
      "fix_228596_editFeature": 0,
      "fix-226056": 0,
      "fix-hideAllLayerObjects-remove-label": 0,
      "fix-icons-and-styles": 0,
      "fix-icons-toggler-styles": 0,
      "fix-rights": 0,
      "fix-save-odata": 0,
      "fix-search-panel": 0,
      "fix-styles": 0,
      "fix-tests": 0,
      "gh-pages": 0,
      "history-fix2": 0,
      "history-layers": 0,
      "label-styles": 0,
      "maplayer-extra-button": 0,
      "master": 0,
      "show_or_hide_buttons": 0,
      "smartForest": 0,
      "style-fix0107": 0,
      "task-trello-281": 0,
      "wi_287_labelForMultiObject": 0,
      "wi_227262_fixIntersectionPanel": 0,
      "wi_228049_fixSearch": 0,
      "wi_228049_setViewForGridLayer": 0,
      "wi_228058_loadFromMap": 0,
      "wi_228958_error": 0,
      "wms-canvas-test": 0
    },
    "branch deviation": {
      "Fix-styles": 118,
      "add_backgroundLayer": 147,
      "api_bookmarks": 675,
      "change-ui-dropdown-on-flexberry-dropdown": 308,
      "check-all-visibility": 330,
      "dependabot/npm_and_yarn/cached-path-relative-1.1.0": 231,
      "dependabot/npm_and_yarn/dexie-3.2.2": 115,
      "dependabot/npm_and_yarn/follow-redirects-1.14.8": 214,
      "dependabot/npm_and_yarn/handlebars-4.7.7": 217,
      "dependabot/npm_and_yarn/moment-2.29.4": 3,
      "dependabot/npm_and_yarn/moment-timezone-0.5.35": 3,
      "dependabot/npm_and_yarn/mout-1.2.3": 218,
      "dependabot/npm_and_yarn/shell-quote-1.7.3": 85,
      "develop": 0,
      "dropdown-on-gis-search-form": 307,
      "edit-form-at-attrs-panel": 294,
      "feature_228064_identificationAndSearch": 0,
      "feature_228586_Identification_By_Area": 7,
      "feature-161988-add-user-labels": 1505,
      "feature-228065-blind-instrument-edit": 10,
      "feature-add-to-aishowFeatureEditForm": 7,
      "feature-ember-update": 77,
      "feature-ember-update-tests": 284,
      "feature-tile-export": 583,
      "fix_edit_maplayer": 142,
      "fix_layerFilter": 84,
      "fix_layerZoomSettings": 148,
      "fix_reloadLayerWithFilter": 198,
      "fix_226713_intersectionForm": 35,
      "fix_227603_mapSearch": 31,
      "fix_228596_editFeature": 3,
      "fix-226056": 35,
      "fix-hideAllLayerObjects-remove-label": 172,
      "fix-icons-and-styles": 80,
      "fix-icons-toggler-styles": 59,
      "fix-rights": 98,
      "fix-save-odata": 162,
      "fix-search-panel": 143,
      "fix-styles": 135,
      "fix-tests": 71,
      "gh-pages": -1,
      "history-fix2": 322,
      "history-layers": 324,
      "label-styles": 144,
      "maplayer-extra-button": 333,
      "master": 387,
      "show_or_hide_buttons": 475,
      "smartForest": 211,
      "style-fix0107": 77,
      "task-trello-281": 80,
      "wi_287_labelForMultiObject": 0,
      "wi_227262_fixIntersectionPanel": 115,
      "wi_228049_fixSearch": 56,
      "wi_228049_setViewForGridLayer": 34,
      "wi_228058_loadFromMap": 1,
      "wi_228958_error": 0,
      "wms-canvas-test": 514
    },
    "unsynced activity": {
      "Fix-styles": 0,
      "add_backgroundLayer": 0,
      "api_bookmarks": 0,
      "change-ui-dropdown-on-flexberry-dropdown": 0,
      "check-all-visibility": 0,
      "dependabot/npm_and_yarn/cached-path-relative-1.1.0": 0,
      "dependabot/npm_and_yarn/dexie-3.2.2": 0,
      "dependabot/npm_and_yarn/follow-redirects-1.14.8": 0,
      "dependabot/npm_and_yarn/handlebars-4.7.7": 0,
      "dependabot/npm_and_yarn/moment-2.29.4": 0,
      "dependabot/npm_and_yarn/moment-timezone-0.5.35": 0,
      "dependabot/npm_and_yarn/mout-1.2.3": 0,
      "dependabot/npm_and_yarn/shell-quote-1.7.3": 0,
      "develop": 0,
      "dropdown-on-gis-search-form": 0,
      "edit-form-at-attrs-panel": 0,
      "feature_228064_identificationAndSearch": 0,
      "feature_228586_Identification_By_Area": 0,
      "feature-161988-add-user-labels": 0,
      "feature-228065-blind-instrument-edit": 0,
      "feature-add-to-aishowFeatureEditForm": 0,
      "feature-ember-update": 0,
      "feature-ember-update-tests": 0,
      "feature-tile-export": 0,
      "fix_edit_maplayer": 0,
      "fix_layerFilter": 0,
      "fix_layerZoomSettings": 0,
      "fix_reloadLayerWithFilter": 0,
      "fix_226713_intersectionForm": 0,
      "fix_227603_mapSearch": 0,
      "fix_228596_editFeature": 0,
      "fix-226056": 0,
      "fix-hideAllLayerObjects-remove-label": 0,
      "fix-icons-and-styles": 0,
      "fix-icons-toggler-styles": 0,
      "fix-rights": 0,
      "fix-save-odata": 0,
      "fix-search-panel": 0,
      "fix-styles": 0,
      "fix-tests": 0,
      "gh-pages": 0,
      "history-fix2": 0,
      "history-layers": 0,
      "label-styles": 0,
      "maplayer-extra-button": 0,
      "master": 0,
      "show_or_hide_buttons": 0,
      "smartForest": 0,
      "style-fix0107": 0,
      "task-trello-281": 0,
      "wi_287_labelForMultiObject": 0,
      "wi_227262_fixIntersectionPanel": 0,
      "wi_228049_fixSearch": 0,
      "wi_228049_setViewForGridLayer": 0,
      "wi_228058_loadFromMap": 0,
      "wi_228958_error": 0,
      "wms-canvas-test": 0
    },
    "classification": {
      "missed activity": {
        "medium_severity": [],
        "high_severity": []
      },
      "branch deviation": {
        "medium_severity": [
          "change-ui-dropdown-on-flexberry-dropdown",
          "check-all-visibility",
          "dropdown-on-gis-search-form",
          "edit-form-at-attrs-panel",
          "feature-ember-update-tests",
          "history-fix2",
          "history-layers",
          "maplayer-extra-button",
          "master",
          "show_or_hide_buttons",
          "wms-canvas-test"
        ],
        "high_severity": [
          "api_bookmarks",
          "feature-161988-add-user-labels",
          "feature-tile-export"
        ]
      },
      "unsynced activity": {
        "medium_severity": [],
        "high_severity": []
      }
    },
    "build_count": 2
  },
  "broken_release": {
    "Build and deploy": {
      "data": [
        {
          "started_at": "2021-06-18T11:11:31Z",
          "used_tool": "Github Actions",
          "number": 20
        }
      ],
      "tool": "Github Actions",
      "release_build_count": 1
    }
  },
  "skip_failing_tests": {}
}