{
  "slow_build": {
    "js-buy-sdk": {
      "data": {
        "2021-04-12T15:34:59Z": 81500.0
      },
      "tool": "TravisCI",
      "total avg": 81500.0,
      "quartiles": {
        "q1": 81500.0,
        "q3": 81500.0,
        "iqr": 0.0
      },
      "classification": {
        "high_severity": {
          "543": 106000,
          "544": 104000
        },
        "medium_severity": {}
      }
    }
  },
  "late_merging": {
    "missed activity": {
      "0.2.x": 0,
      "2.0.0-with-tags": 0,
      "2.7.0-docs": 1081,
      "add-compare-at-price": 1683,
      "add-custom-source-header": 1067,
      "add-shipping-address-update-example": 1239,
      "add-translation": 934,
      "alp": 0,
      "bump_schema": 1218,
      "bump-docs-2.5.0": 1136,
      "bump-graphql-js-client": 932,
      "bump-graphql-js-client-version-for-first-var-issue": 1569,
      "changelog-v2020-07": 751,
      "checkout-reject-promise": 1569,
      "checkout-shipping-address-update": 1261,
      "checkout-user-errors-codes": 1259,
      "circle-ci-remove-c9dcda": 0,
      "convert-api-docs-to-md": 0,
      "dependabot/npm_and_yarn/aws-sdk-2.814.0": 0,
      "dependabot/npm_and_yarn/ecstatic-2.2.2": 0,
      "dependabot/npm_and_yarn/elliptic-6.5.4": 0,
      "dependabot/npm_and_yarn/handlebars-4.7.7": 0,
      "dependabot/npm_and_yarn/http-proxy-1.18.1": 0,
      "dependabot/npm_and_yarn/ini-1.3.8": 0,
      "dependabot/npm_and_yarn/is-my-json-valid-2.20.6": 0,
      "dependabot/npm_and_yarn/merge-1.2.1": 0,
      "dependabot/npm_and_yarn/minimist-1.2.6": 0,
      "dependabot/npm_and_yarn/moment-2.29.4": 0,
      "dependabot/npm_and_yarn/node-fetch-2.6.7": 0,
      "dependabot/npm_and_yarn/path-parse-1.0.7": 0,
      "dependabot/npm_and_yarn/set-getter-0.1.1": 0,
      "dependabot/npm_and_yarn/tar-4.4.19": 0,
      "dependabot/npm_and_yarn/tree-kill-1.2.2": 0,
      "discount-application-value": 1081,
      "docs-for-2.2.0": 1218,
      "feature/ie9-error-messaging": 0,
      "feature/node-tests": 0,
      "feature_s3-dir-name": 2323,
      "fix-error-messages": 1612,
      "gh-pages": 0,
      "gitignore-sasscache": 0,
      "graph-list": 0,
      "graphql": 0,
      "installation-version-clarification": 174,
      "lokka-graphql": 0,
      "master": 0,
      "money-v2-variant-fields": 1084,
      "permalink_checkout_use_access_token": 2052,
      "profile-field-usage": 0,
      "readme": 0,
      "refactor-to-graphql": 0,
      "release_2_8_1": 0,
      "remove-product-load": 1569,
      "replace_deprecated_field_usage": 0,
      "revert-6-cart-example-with-variants": 0,
      "services-db/remove-director": 1431,
      "shipit-deploy/production": 0,
      "unit-price-fields": 933,
      "update_owner": 0,
      "update_reference_docs": 2305,
      "update-SFAPI-v2021-10": 273,
      "update-SFAPI-v2022-01": 203,
      "update-SFAPI-v2022-04": 115,
      "update-changelog-2.16.1": 23,
      "update-changelog-v2.7.1": 1067,
      "update-changelog-v2.7.2": 1044,
      "update-changelog-v2.9.2": 857,
      "update-changelog-v2.14.0": 203,
      "update-changelog-v2021-10": 273,
      "update-code-of-conduct-report-link": 843,
      "update-deprecated-fields": 0,
      "update-language-setting": 857,
      "update-schema-changelong-v2.15.1": 115,
      "update-sfapi-v2020-07": 751,
      "update-sfapi-v2022-07": 23,
      "update-sfapi-v2022-10": 0,
      "update-shipit-file-name": 23,
      "upgrade-to-slimmer-js-schema": 0,
      "use-yarn-exclusively": 1007,
      "v1.0alpha": 0,
      "v1.0beta": 1696,
      "v2.0.0_release": 0,
      "version-3": 0,
      "yomi-test-fs-extra": 0
    },
    "branch deviation": {
      "0.2.x": 2115,
      "2.0.0-with-tags": 1294,
      "2.7.0-docs": 1081,
      "add-compare-at-price": 1683,
      "add-custom-source-header": 1081,
      "add-shipping-address-update-example": 1239,
      "add-translation": 934,
      "alp": 1850,
      "bump_schema": 1218,
      "bump-docs-2.5.0": 1136,
      "bump-graphql-js-client": 932,
      "bump-graphql-js-client-version-for-first-var-issue": 1569,
      "changelog-v2020-07": 751,
      "checkout-reject-promise": 1570,
      "checkout-shipping-address-update": 1261,
      "checkout-user-errors-codes": 1260,
      "circle-ci-remove-c9dcda": 1501,
      "convert-api-docs-to-md": 2158,
      "dependabot/npm_and_yarn/aws-sdk-2.814.0": 254,
      "dependabot/npm_and_yarn/ecstatic-2.2.2": 331,
      "dependabot/npm_and_yarn/elliptic-6.5.4": 331,
      "dependabot/npm_and_yarn/handlebars-4.7.7": 331,
      "dependabot/npm_and_yarn/http-proxy-1.18.1": 689,
      "dependabot/npm_and_yarn/ini-1.3.8": 23,
      "dependabot/npm_and_yarn/is-my-json-valid-2.20.6": 115,
      "dependabot/npm_and_yarn/merge-1.2.1": 331,
      "dependabot/npm_and_yarn/minimist-1.2.6": 115,
      "dependabot/npm_and_yarn/moment-2.29.4": 21,
      "dependabot/npm_and_yarn/node-fetch-2.6.7": 115,
      "dependabot/npm_and_yarn/path-parse-1.0.7": 351,
      "dependabot/npm_and_yarn/set-getter-0.1.1": 402,
      "dependabot/npm_and_yarn/tar-4.4.19": 23,
      "dependabot/npm_and_yarn/tree-kill-1.2.2": 691,
      "discount-application-value": 1084,
      "docs-for-2.2.0": 1218,
      "feature/ie9-error-messaging": 2110,
      "feature/node-tests": 2037,
      "feature_s3-dir-name": 2323,
      "fix-error-messages": 1612,
      "gh-pages": 2228,
      "gitignore-sasscache": 2275,
      "graph-list": 2155,
      "graphql": 2131,
      "installation-version-clarification": 176,
      "lokka-graphql": 2215,
      "master": 0,
      "money-v2-variant-fields": 1085,
      "permalink_checkout_use_access_token": 2052,
      "profile-field-usage": 1907,
      "readme": 2323,
      "refactor-to-graphql": 1953,
      "release_2_8_1": 986,
      "remove-product-load": 1569,
      "replace_deprecated_field_usage": 1302,
      "revert-6-cart-example-with-variants": 2326,
      "services-db/remove-director": 1431,
      "shipit-deploy/production": 23,
      "unit-price-fields": 933,
      "update_owner": 1431,
      "update_reference_docs": 2305,
      "update-SFAPI-v2021-10": 302,
      "update-SFAPI-v2022-01": 204,
      "update-SFAPI-v2022-04": 119,
      "update-changelog-2.16.1": 23,
      "update-changelog-v2.7.1": 1067,
      "update-changelog-v2.7.2": 1044,
      "update-changelog-v2.9.2": 857,
      "update-changelog-v2.14.0": 203,
      "update-changelog-v2021-10": 273,
      "update-code-of-conduct-report-link": 843,
      "update-deprecated-fields": 1350,
      "update-language-setting": 857,
      "update-schema-changelong-v2.15.1": 115,
      "update-sfapi-v2020-07": 751,
      "update-sfapi-v2022-07": 23,
      "update-sfapi-v2022-10": -26,
      "update-shipit-file-name": 23,
      "upgrade-to-slimmer-js-schema": 1919,
      "use-yarn-exclusively": 1010,
      "v1.0alpha": 1781,
      "v1.0beta": 1697,
      "v2.0.0_release": 1359,
      "version-3": 1204,
      "yomi-test-fs-extra": 2183
    },
    "unsynced activity": {
      "0.2.x": 0,
      "2.0.0-with-tags": 0,
      "2.7.0-docs": -1,
      "add-compare-at-price": -1,
      "add-custom-source-header": -14,
      "add-shipping-address-update-example": -1,
      "add-translation": -1,
      "alp": 0,
      "bump_schema": -1,
      "bump-docs-2.5.0": -1,
      "bump-graphql-js-client": -1,
      "bump-graphql-js-client-version-for-first-var-issue": -1,
      "changelog-v2020-07": -1,
      "checkout-reject-promise": -1,
      "checkout-shipping-address-update": -1,
      "checkout-user-errors-codes": -2,
      "circle-ci-remove-c9dcda": 0,
      "convert-api-docs-to-md": 0,
      "dependabot/npm_and_yarn/aws-sdk-2.814.0": 0,
      "dependabot/npm_and_yarn/ecstatic-2.2.2": 0,
      "dependabot/npm_and_yarn/elliptic-6.5.4": 0,
      "dependabot/npm_and_yarn/handlebars-4.7.7": 0,
      "dependabot/npm_and_yarn/http-proxy-1.18.1": 0,
      "dependabot/npm_and_yarn/ini-1.3.8": 0,
      "dependabot/npm_and_yarn/is-my-json-valid-2.20.6": 0,
      "dependabot/npm_and_yarn/merge-1.2.1": 0,
      "dependabot/npm_and_yarn/minimist-1.2.6": 0,
      "dependabot/npm_and_yarn/moment-2.29.4": 0,
      "dependabot/npm_and_yarn/node-fetch-2.6.7": 0,
      "dependabot/npm_and_yarn/path-parse-1.0.7": 0,
      "dependabot/npm_and_yarn/set-getter-0.1.1": 0,
      "dependabot/npm_and_yarn/tar-4.4.19": 0,
      "dependabot/npm_and_yarn/tree-kill-1.2.2": 0,
      "discount-application-value": -3,
      "docs-for-2.2.0": -1,
      "feature/ie9-error-messaging": 0,
      "feature/node-tests": 0,
      "feature_s3-dir-name": 0,
      "fix-error-messages": -1,
      "gh-pages": 0,
      "gitignore-sasscache": 0,
      "graph-list": 0,
      "graphql": 0,
      "installation-version-clarification": -2,
      "lokka-graphql": 0,
      "master": 0,
      "money-v2-variant-fields": -1,
      "permalink_checkout_use_access_token": 0,
      "profile-field-usage": 0,
      "readme": 0,
      "refactor-to-graphql": 0,
      "release_2_8_1": 0,
      "remove-product-load": -1,
      "replace_deprecated_field_usage": 0,
      "revert-6-cart-example-with-variants": 0,
      "services-db/remove-director": -1,
      "shipit-deploy/production": 0,
      "unit-price-fields": -1,
      "update_owner": 0,
      "update_reference_docs": -1,
      "update-SFAPI-v2021-10": -29,
      "update-SFAPI-v2022-01": -1,
      "update-SFAPI-v2022-04": -5,
      "update-changelog-2.16.1": -1,
      "update-changelog-v2.7.1": -1,
      "update-changelog-v2.7.2": -1,
      "update-changelog-v2.9.2": -1,
      "update-changelog-v2.14.0": -1,
      "update-changelog-v2021-10": -1,
      "update-code-of-conduct-report-link": -1,
      "update-deprecated-fields": 0,
      "update-language-setting": -1,
      "update-schema-changelong-v2.15.1": -1,
      "update-sfapi-v2020-07": -1,
      "update-sfapi-v2022-07": -1,
      "update-sfapi-v2022-10": 0,
      "update-shipit-file-name": -1,
      "upgrade-to-slimmer-js-schema": 0,
      "use-yarn-exclusively": -4,
      "v1.0alpha": 0,
      "v1.0beta": -1,
      "v2.0.0_release": 0,
      "version-3": 0,
      "yomi-test-fs-extra": 0
    },
    "classification": {
      "missed activity": {
        "medium_severity": [
          "2.7.0-docs",
          "add-compare-at-price",
          "add-custom-source-header",
          "add-shipping-address-update-example",
          "bump_schema",
          "bump-docs-2.5.0",
          "bump-graphql-js-client-version-for-first-var-issue",
          "checkout-reject-promise",
          "checkout-shipping-address-update",
          "checkout-user-errors-codes",
          "discount-application-value",
          "docs-for-2.2.0",
          "feature_s3-dir-name",
          "fix-error-messages",
          "money-v2-variant-fields",
          "permalink_checkout_use_access_token",
          "remove-product-load",
          "services-db/remove-director",
          "update_reference_docs",
          "update-changelog-v2.7.1",
          "v1.0beta"
        ],
        "high_severity": []
      },
      "branch deviation": {
        "medium_severity": [
          "0.2.x",
          "alp",
          "convert-api-docs-to-md",
          "feature/ie9-error-messaging",
          "feature/node-tests",
          "feature_s3-dir-name",
          "gh-pages",
          "gitignore-sasscache",
          "graph-list",
          "graphql",
          "lokka-graphql",
          "permalink_checkout_use_access_token",
          "profile-field-usage",
          "readme",
          "refactor-to-graphql",
          "revert-6-cart-example-with-variants",
          "update_reference_docs",
          "upgrade-to-slimmer-js-schema",
          "v1.0alpha",
          "v1.0beta",
          "yomi-test-fs-extra"
        ],
        "high_severity": []
      },
      "unsynced activity": {
        "medium_severity": [
          "2.7.0-docs",
          "add-compare-at-price",
          "add-shipping-address-update-example",
          "add-translation",
          "bump_schema",
          "bump-docs-2.5.0",
          "bump-graphql-js-client",
          "bump-graphql-js-client-version-for-first-var-issue",
          "changelog-v2020-07",
          "checkout-reject-promise",
          "checkout-shipping-address-update",
          "docs-for-2.2.0",
          "fix-error-messages",
          "money-v2-variant-fields",
          "remove-product-load",
          "services-db/remove-director",
          "unit-price-fields",
          "update_reference_docs",
          "update-SFAPI-v2022-01",
          "update-changelog-2.16.1",
          "update-changelog-v2.7.1",
          "update-changelog-v2.7.2",
          "update-changelog-v2.9.2",
          "update-changelog-v2.14.0",
          "update-changelog-v2021-10",
          "update-code-of-conduct-report-link",
          "update-language-setting",
          "update-schema-changelong-v2.15.1",
          "update-sfapi-v2020-07",
          "update-sfapi-v2022-07",
          "update-shipit-file-name",
          "v1.0beta"
        ],
        "high_severity": [
          "add-custom-source-header",
          "checkout-user-errors-codes",
          "discount-application-value",
          "installation-version-clarification",
          "update-SFAPI-v2021-10",
          "update-SFAPI-v2022-04",
          "use-yarn-exclusively"
        ]
      }
    },
    "build_count": 1
  },
  "broken_release": {
    "js-buy-sdk": {
      "data": [
        {
          "started_at": "2021-04-19T10:20:09Z",
          "used_tool": "TravisCI",
          "number": 545
        },
        {
          "started_at": "2021-04-19T10:29:10Z",
          "used_tool": "TravisCI",
          "number": 546
        }
      ],
      "tool": "TravisCI",
      "release_build_count": 3
    }
  },
  "skip_failing_tests": {}
}